cgvrp/__init__.py
cgvrp/_rcspp.cp312-win_amd64.pyd
cgvrp/_rcspp.pyi
cgvrp/vrptw/__init__.py
cgvrp/vrptw/cg.py
cgvrp/vrptw/model.py
cgvrp/vrptw/problem.py
cgvrp/vrptw/result.py
cgvrp/vrptw/route.py
cgvrp/vrptw_pricing.pyi
cg_vrp-0.1.0.dist-info/METADATA
cg_vrp-0.1.0.dist-info/WHEEL
cg_vrp-0.1.0.dist-info/RECORD
