Metadata-Version: 2.4
Name: cg-vrp
Version: 0.1.0
Summary: Column generation for the Vechile-Routing-Problem.
Author-Email: littleqjy <littleqjy@gmail.com>
License-Expression: MIT
Classifier: Programming Language :: Python :: 3
Classifier: Operating System :: OS Independent
Classifier: Intended Audience :: Developers
Classifier: Intended Audience :: Science/Research
Classifier: Topic :: Scientific/Engineering
Project-URL: Homepage, https://github.com/littleQiu22/cg-vrp
Requires-Python: >=3.9
Requires-Dist: networkx
Requires-Dist: pulp
